LICENSE
README.md
setup.py
aiogram_pagination/__init__.py
aiogram_pagination.egg-info/PKG-INFO
aiogram_pagination.egg-info/SOURCES.txt
aiogram_pagination.egg-info/dependency_links.txt
aiogram_pagination.egg-info/requires.txt
aiogram_pagination.egg-info/top_level.txt
aiogram_pagination/callback_stack/__init__.py
aiogram_pagination/callback_stack/abbreviated_callback_stack.py
aiogram_pagination/callback_stack/abstract_callback_stack.py
aiogram_pagination/callback_stack/callback_stack.py
aiogram_pagination/callback_stack/simple_callback_stack.py
aiogram_pagination/callback_storage/__init__.py
aiogram_pagination/callback_storage/abstract_storage.py
aiogram_pagination/callback_storage/builtin_storage.py
aiogram_pagination/callback_storage/redis_storage.py
aiogram_pagination/callback_storage/sqlite_storage.py
aiogram_pagination/data/__init__.py
aiogram_pagination/data/callback_configurator.py
aiogram_pagination/data/config.py
aiogram_pagination/data/loader.py
aiogram_pagination/on_startup/__init__.py
aiogram_pagination/on_startup/callback_daemon.py
aiogram_pagination/on_startup/on_startup.py
aiogram_pagination/utils/__init__.py
aiogram_pagination/utils/callback_stack_factory.py
aiogram_pagination/utils/counter.py
aiogram_pagination/utils/custom_notation.py
aiogram_pagination/utils/singlton.py
aiogram_pagination/utils/db_api/__init__.py
aiogram_pagination/utils/db_api/engine.py
aiogram_pagination/utils/db_api/schemas.py