Metadata-Version: 2.1
Name: aiogram-pagination
Version: 0.1.9
Summary: Module for deep pagination in an aiogram bot
Home-page: https://github.com/altroncode/aiogram-pagination
Author: altcode
Author-email: cosmosx1328@gmail.com
License: UNKNOWN
Platform: UNKNOWN
Classifier: Programming Language :: Python :: 3.7
Classifier: Programming Language :: Python :: 3.8
Classifier: Programming Language :: Python :: 3.9
Classifier: License :: OSI Approved :: MIT License
Classifier: Operating System :: OS Independent
Classifier: Intended Audience :: Developers
Classifier: Topic :: Software Development :: Libraries
License-File: LICENSE
